omarradwan/__init__.py
omarradwan-0.1.dist-info/METADATA
omarradwan-0.1.dist-info/WHEEL
omarradwan-0.1.dist-info/top_level.txt
omarradwan-0.1.dist-info/RECORD
