Metadata-Version: 2.4
Name: omarradwan
Version: 0.1
Summary: simple library in python for test
Classifier: Programming Language :: Python :: 3
Classifier: Operating System :: OS Independent
Classifier: License :: OSI Approved :: MIT License
Dynamic: classifier
Dynamic: summary
